fast_label_studio/__init__.py
fast_label_studio/brush.py
fast_label_studio/segmentation_model.py
fast_label_studio-0.4.0.dist-info/WHEEL
fast_label_studio-0.4.0.dist-info/METADATA
fast_label_studio-0.4.0.dist-info/RECORD
